{"variants":[{"paths":["\/tutorials\/swiftinsg\/0-todolists"],"traits":[{"interfaceLanguage":"swift"}]}],"schemaVersion":{"major":0,"minor":3,"patch":0},"sections":[{"content":[{"type":"paragraph","inlineContent":[{"type":"text","text":"This tutorial covers how to use create a "},{"type":"codeVoice","code":"Todo"},{"type":"text","text":" struct, using "},{"type":"codeVoice","code":"List"},{"type":"text","text":"s to iterate over an array of "},{"type":"codeVoice","code":"todos"},{"type":"text","text":" and embedding it in a "},{"type":"codeVoice","code":"NavigationView"},{"type":"text","text":" with a "},{"type":"codeVoice","code":".navigationTitle"},{"type":"text","text":"."}]}],"estimatedTimeInMinutes":20,"title":"Listing Todos","image":"","chapter":"Creating a Todo List app","kind":"hero","backgroundImage":""},{"kind":"tasks","tasks":[{"anchor":"Creating-a-Project","title":"Creating a Project","contentSection":[{"kind":"contentAndMedia","content":[{"type":"paragraph","inlineContent":[{"type":"text","text":"This section just covers how to set up and create a project. This is similar to what we have done in the "},{"type":"reference","isActive":true,"identifier":"..\/flag-raising"},{"type":"text","text":", "},{"type":"reference","isActive":true,"identifier":"..\/quiz-app"},{"type":"text","text":" & "},{"type":"reference","isActive":true,"identifier":"..\/friends"},{"type":"text","text":" tutorials."}]}],"mediaPosition":"trailing","media":""}],"stepsSection":[{"code":null,"content":[{"type":"paragraph","inlineContent":[{"type":"text","text":"In Xcode, "},{"type":"strong","inlineContent":[{"type":"text","text":"Create a new Xcode project"}]},{"type":"text","text":"."}]}],"caption":[{"type":"aside","style":"note","content":[{"type":"paragraph","inlineContent":[{"type":"text","text":"Alternatively, you can go to "},{"type":"strong","inlineContent":[{"type":"text","text":"File → New → Project…"}]},{"type":"text","text":" or "},{"type":"strong","inlineContent":[{"type":"text","text":"⌘⇧N"}]},{"type":"text","text":" (Command-Shift-N)"}]}]}],"type":"step","runtimePreview":null,"media":"shared-new project.png"},{"code":null,"content":[{"type":"paragraph","inlineContent":[{"type":"text","text":"Set the platform as "},{"type":"strong","inlineContent":[{"type":"text","text":"iOS"}]},{"type":"text","text":" and select "},{"type":"strong","inlineContent":[{"type":"text","text":"App"}]},{"type":"text","text":"."}]}],"caption":[],"type":"step","runtimePreview":null,"media":"shared-select app.png"},{"code":null,"content":[{"type":"paragraph","inlineContent":[{"type":"text","text":"Set the Product Name as "},{"type":"strong","inlineContent":[{"type":"text","text":"“Todos”"}]},{"type":"text","text":" and ensure that your interface is "},{"type":"strong","inlineContent":[{"type":"text","text":"SwiftUI"}]},{"type":"text","text":" and your life cycle is "},{"type":"strong","inlineContent":[{"type":"text","text":"SwiftUI App"}]},{"type":"text","text":"."}]}],"caption":[],"type":"step","runtimePreview":null,"media":"todo-ch1-lists-s1-2-configuring project.png"},{"code":null,"content":[{"type":"paragraph","inlineContent":[{"type":"text","text":"You’re all set!"}]}],"caption":[],"type":"step","runtimePreview":null,"media":"todo-ch1-lists-s1-3-create project.png"}]},{"anchor":"Create-a-Todo","title":"Create a Todo","contentSection":[{"kind":"contentAndMedia","content":[{"type":"paragraph","inlineContent":[{"type":"text","text":"Create a "},{"type":"codeVoice","code":"Todo"},{"type":"text","text":" struct to store each todo item and conform it to "},{"type":"codeVoice","code":"Identifiable"},{"type":"text","text":" as it will be iterated through in a "},{"type":"codeVoice","code":"List"},{"type":"text","text":"."}]}],"mediaPosition":"trailing","media":""}],"stepsSection":[{"anchor":"Create-a-new-Swift-file","level":2,"type":"heading","text":"Create a new Swift file"},{"code":null,"content":[{"type":"paragraph","inlineContent":[{"type":"text","text":"Create a new Swift file. In the menubar, go to "},{"type":"strong","inlineContent":[{"type":"text","text":"File → New → File…"}]},{"type":"text","text":"."}]}],"caption":[{"type":"aside","style":"note","content":[{"type":"paragraph","inlineContent":[{"type":"text","text":"Alternatively, you may use ⌘N (Command-N) to create a new file."}]}]}],"type":"step","runtimePreview":null,"media":"todo-ch1-lists-s2-0-new file.png"},{"code":null,"content":[{"type":"paragraph","inlineContent":[{"type":"text","text":"Select New "},{"type":"strong","inlineContent":[{"type":"text","text":"Swift"}]},{"type":"text","text":" file."}]}],"caption":[],"type":"step","runtimePreview":null,"media":"shared-new swift file.png"},{"code":null,"content":[{"type":"paragraph","inlineContent":[{"type":"text","text":"Name the file "},{"type":"codeVoice","code":"Todo.swift"},{"type":"text","text":" and create it."}]}],"caption":[],"type":"step","runtimePreview":null,"media":"todo-ch1-lists-s2-2-save.png"},{"code":"todo-ch1-lists-s2-3-Todo.swift","content":[{"type":"paragraph","inlineContent":[{"type":"text","text":"This is what you should see after you created your new file."}]}],"caption":[],"type":"step","runtimePreview":null,"media":null},{"anchor":"Setting-up-Todo-struct","level":2,"type":"heading","text":"Setting up Todo struct"},{"code":"todo-ch1-lists-s2-4-Todo.swift","content":[{"type":"paragraph","inlineContent":[{"type":"text","text":"Create a "},{"type":"codeVoice","code":"Todo"},{"type":"text","text":" struct. This struct will be used to store each individual todo."}]}],"caption":[],"type":"step","runtimePreview":null,"media":null},{"code":"todo-ch1-lists-s2-5-Todo.swift","content":[{"type":"paragraph","inlineContent":[{"type":"text","text":"Within each "},{"type":"codeVoice","code":"Todo"},{"type":"text","text":", there are 2 properties. The "},{"type":"codeVoice","code":"title"},{"type":"text","text":" and whether or not the todo "},{"type":"codeVoice","code":"isCompleted"},{"type":"text","text":"."}]}],"caption":[],"type":"step","runtimePreview":null,"media":null},{"anchor":"Conforming-to-Identifiable","level":2,"type":"heading","text":"Conforming to Identifiable"},{"type":"paragraph","inlineContent":[{"type":"text","text":"As "},{"type":"codeVoice","code":"Todo"},{"type":"text","text":" will be used within a "},{"type":"codeVoice","code":"List"},{"type":"text","text":", it will need to conform to the "},{"type":"reference","isActive":true,"identifier":"https:\/\/developer.apple.com\/documentation\/swift\/identifiable\/"},{"type":"text","text":" protocol."}]},{"code":"todo-ch1-lists-s2-6-Todo.swift","content":[{"type":"paragraph","inlineContent":[{"type":"text","text":"Add "},{"type":"codeVoice","code":": Identifiable"},{"type":"text","text":" to allow the "},{"type":"codeVoice","code":"Todo"},{"type":"text","text":" struct to conform to the Identifable procol."}]}],"caption":[],"type":"step","runtimePreview":null,"media":null},{"anchor":"Creating-an-array-of-Todos","level":2,"type":"heading","text":"Creating an array of Todos"},{"type":"paragraph","inlineContent":[{"type":"text","text":"Create an array of sample Todos."}]},{"code":"todo-ch1-lists-s2-7-ContentView.swift","content":[{"type":"paragraph","inlineContent":[{"type":"text","text":"Open the "},{"type":"codeVoice","code":"ContentView.swift"},{"type":"text","text":" file."}]}],"caption":[],"type":"step","runtimePreview":"todo-ch1-lists-s2-7-Preview.png","media":null},{"code":"todo-ch1-lists-s2-8-ContentView.swift","content":[{"type":"paragraph","inlineContent":[{"type":"text","text":"Create a "},{"type":"codeVoice","code":"@State"},{"type":"text","text":" variable with an array of sample "},{"type":"codeVoice","code":"Todo"},{"type":"text","text":"s"}]}],"caption":[],"type":"step","runtimePreview":"todo-ch1-lists-s2-8-Preview.png","media":null}]},{"anchor":"Creating-a-List","title":"Creating a List","contentSection":[{"kind":"contentAndMedia","content":[{"type":"paragraph","inlineContent":[{"type":"text","text":"Create a "},{"type":"codeVoice","code":"List"},{"type":"text","text":" to display the contents of the "},{"type":"codeVoice","code":"todos"},{"type":"text","text":" array."}]}],"mediaPosition":"trailing","media":""}],"stepsSection":[{"code":"todo-ch1-lists-s3-0-ContentView.swift","content":[{"type":"paragraph","inlineContent":[{"type":"text","text":"Open the "},{"type":"codeVoice","code":"ContentView.swift"},{"type":"text","text":" file."}]}],"caption":[],"type":"step","runtimePreview":"todo-ch1-lists-s3-0-Preview.png","media":null},{"code":"todo-ch1-lists-s3-1-ContentView.swift","content":[{"type":"paragraph","inlineContent":[{"type":"text","text":"Create a "},{"type":"codeVoice","code":"List"},{"type":"text","text":" iterating through the "},{"type":"codeVoice","code":"todos"},{"type":"text","text":" array and displaying each "},{"type":"codeVoice","code":"Todo"},{"type":"text","text":"."}]}],"caption":[],"type":"step","runtimePreview":"todo-ch1-lists-s3-1-Preview.png","media":null}]},{"anchor":"Embedding-in-a-NavigationView","title":"Embedding in a NavigationView","contentSection":[{"kind":"contentAndMedia","content":[{"type":"paragraph","inlineContent":[{"type":"text","text":"Embed the "},{"type":"codeVoice","code":"List"},{"type":"text","text":" in a "},{"type":"codeVoice","code":"NavigationView"},{"type":"text","text":" to provide it with a nice "},{"type":"codeVoice","code":".navigationTitle"},{"type":"text","text":"."}]}],"mediaPosition":"trailing","media":""}],"stepsSection":[{"code":"todo-ch1-lists-s4-0-ContentView.swift","content":[{"type":"paragraph","inlineContent":[{"type":"text","text":"Open the "},{"type":"codeVoice","code":"ContentView.swift"},{"type":"text","text":" file."}]}],"caption":[],"type":"step","runtimePreview":"todo-ch1-lists-s4-0-Preview.png","media":null},{"code":"todo-ch1-lists-s4-1-ContentView.swift","content":[{"type":"paragraph","inlineContent":[{"type":"text","text":"Embed the "},{"type":"codeVoice","code":"List"},{"type":"text","text":" in a "},{"type":"codeVoice","code":"NavigationView"},{"type":"text","text":"."}]}],"caption":[],"type":"step","runtimePreview":"todo-ch1-lists-s4-1-Preview.png","media":null},{"code":"todo-ch1-lists-s4-2-ContentView.swift","content":[{"type":"paragraph","inlineContent":[{"type":"text","text":"Add a "},{"type":"codeVoice","code":".navigationTitle"},{"type":"text","text":" called "},{"type":"strong","inlineContent":[{"type":"text","text":"“Todos”"}]},{"type":"text","text":"."}]}],"caption":[],"type":"step","runtimePreview":"todo-ch1-lists-s4-2-Preview.png","media":null}]}]},{"action":{"overridingTitleInlineContent":[{"type":"text","text":"Get started"}],"isActive":true,"type":"reference","identifier":"doc:\/\/swiftinsg\/tutorials\/swiftinsg\/1-TodoStrikethrough","overridingTitle":"Get started"},"featuredEyebrow":"Tutorial","kind":"callToAction","title":"Striking Off Todos","abstract":[{"type":"text","text":"Add a checkmark using SF Symbols and use the "},{"type":"codeVoice","code":".strikethrough"},{"type":"text","text":" modifier to add a strikethrough when the todo "},{"type":"codeVoice","code":"isCompleted"},{"type":"text","text":"."}]}],"identifier":{"url":"doc:\/\/swiftinsg\/tutorials\/swiftinsg\/0-TodoLists","interfaceLanguage":"swift"},"kind":"project","metadata":{"title":"Listing Todos","categoryPathComponent":"Todo","role":"project","category":"Todo App"},"hierarchy":{"modules":[{"reference":"doc:\/\/swiftinsg\/tutorials\/Todo\/Creating-a-Todo-List-app","projects":[{"reference":"doc:\/\/swiftinsg\/tutorials\/swiftinsg\/0-TodoLists","sections":[{"kind":"task","reference":"doc:\/\/swiftinsg\/tutorials\/swiftinsg\/0-TodoLists#Creating-a-Project"},{"kind":"task","reference":"doc:\/\/swiftinsg\/tutorials\/swiftinsg\/0-TodoLists#Create-a-Todo"},{"kind":"task","reference":"doc:\/\/swiftinsg\/tutorials\/swiftinsg\/0-TodoLists#Creating-a-List"},{"kind":"task","reference":"doc:\/\/swiftinsg\/tutorials\/swiftinsg\/0-TodoLists#Embedding-in-a-NavigationView"}]},{"reference":"doc:\/\/swiftinsg\/tutorials\/swiftinsg\/1-TodoStrikethrough","sections":[{"kind":"task","reference":"doc:\/\/swiftinsg\/tutorials\/swiftinsg\/1-TodoStrikethrough#Adding-a-Checkmark"},{"kind":"task","reference":"doc:\/\/swiftinsg\/tutorials\/swiftinsg\/1-TodoStrikethrough#Adding-a-Strikethrough"},{"kind":"task","reference":"doc:\/\/swiftinsg\/tutorials\/swiftinsg\/1-TodoStrikethrough#Toggling-a-Todo"}]},{"reference":"doc:\/\/swiftinsg\/tutorials\/swiftinsg\/2-TodoManipulation","sections":[{"kind":"task","reference":"doc:\/\/swiftinsg\/tutorials\/swiftinsg\/2-TodoManipulation#Deleting-a-Todo"},{"kind":"task","reference":"doc:\/\/swiftinsg\/tutorials\/swiftinsg\/2-TodoManipulation#Moving-Todos"}]},{"reference":"doc:\/\/swiftinsg\/tutorials\/swiftinsg\/3-TodoNew","sections":[{"kind":"task","reference":"doc:\/\/swiftinsg\/tutorials\/swiftinsg\/3-TodoNew#Creating-a-new-SwiftUI-View"},{"kind":"task","reference":"doc:\/\/swiftinsg\/tutorials\/swiftinsg\/3-TodoNew#Building-a-Form"},{"kind":"task","reference":"doc:\/\/swiftinsg\/tutorials\/swiftinsg\/3-TodoNew#Saving-a-Todo"},{"kind":"task","reference":"doc:\/\/swiftinsg\/tutorials\/swiftinsg\/3-TodoNew#Dismissing-the-Modal"},{"kind":"task","reference":"doc:\/\/swiftinsg\/tutorials\/swiftinsg\/3-TodoNew#Embedding-in-NavigationView"},{"kind":"task","reference":"doc:\/\/swiftinsg\/tutorials\/swiftinsg\/3-TodoNew#Presenting-the-Modal"}]},{"reference":"doc:\/\/swiftinsg\/tutorials\/swiftinsg\/4-TodoPersistence","sections":[{"kind":"task","reference":"doc:\/\/swiftinsg\/tutorials\/swiftinsg\/4-TodoPersistence#Conforming-to-Codable"},{"kind":"task","reference":"doc:\/\/swiftinsg\/tutorials\/swiftinsg\/4-TodoPersistence#Creating-a-Task-Model"},{"kind":"task","reference":"doc:\/\/swiftinsg\/tutorials\/swiftinsg\/4-TodoPersistence#Save-and-Load-Data"}]}]}],"reference":"doc:\/\/swiftinsg\/tutorials\/Todo","paths":[["doc:\/\/swiftinsg\/tutorials\/Todo","doc:\/\/swiftinsg\/tutorials\/Todo\/$volume","doc:\/\/swiftinsg\/tutorials\/Todo\/Creating-a-Todo-List-app"]]},"references":{"todo-ch1-lists-s3-0-ContentView.swift":{"syntax":"swift","content":["import SwiftUI","","struct ContentView: View {","    ","    @State var todos = [Todo(title: \"Feed the cat\"),","                        Todo(title: \"Play with cat\"),","                        Todo(title: \"Get allergies\"),","                        Todo(title: \"Run away from cat\"),","                        Todo(title: \"Get a new cat\")]","    ","    var body: some View {","        Text(\"Hello, world!\")","            .padding()","    }","}","","struct ContentView_Previews: PreviewProvider {","    static var previews: some View {","        ContentView()","    }","}"],"fileName":"ContentView.swift","identifier":"todo-ch1-lists-s3-0-ContentView.swift","type":"file","fileType":"swift","highlights":[]},"doc://swiftinsg/tutorials/swiftinsg/4-TodoPersistence":{"role":"project","title":"Persisting Todos","estimatedTime":"15min","abstract":[{"type":"text","text":"Persistence is not that hard, all you need is some… persistence. HAHHAHAHHAHHHAHAHAH. Persistence refers to the concept of storing data in a way that they will remain there even if you close the app. Currently, when you close the app, any data is thrown away. If you create a new todo, it gets thrown away when you close the app. We want data to persist when the app is closed otherwise the todo list app will be as forgetful as you."}],"identifier":"doc:\/\/swiftinsg\/tutorials\/swiftinsg\/4-TodoPersistence","kind":"project","type":"topic","url":"\/tutorials\/swiftinsg\/4-todopersistence"},"doc://swiftinsg/tutorials/swiftinsg/3-TodoNew#Building-a-Form":{"role":"pseudoSymbol","title":"Building a Form","abstract":[{"type":"text","text":"This tutorial covers how to use "},{"type":"codeVoice","code":"Form"},{"type":"text","text":"s, modals and "},{"type":"codeVoice","code":"@Binding"},{"type":"text","text":" variables to create a new "},{"type":"codeVoice","code":"Todo"},{"type":"text","text":"."}],"identifier":"doc:\/\/swiftinsg\/tutorials\/swiftinsg\/3-TodoNew#Building-a-Form","kind":"section","type":"section","url":"\/tutorials\/swiftinsg\/3-todonew#Building-a-Form"},"../flag-raising":{"title":"Flag Raising","titleInlineContent":[{"type":"text","text":"Flag Raising"}],"type":"link","identifier":"..\/flag-raising","url":"..\/flag-raising"},"doc://swiftinsg/tutorials/swiftinsg/0-TodoLists#Creating-a-Project":{"role":"pseudoSymbol","title":"Creating a Project","abstract":[{"type":"text","text":"This tutorial covers how to use create a "},{"type":"codeVoice","code":"Todo"},{"type":"text","text":" struct, using "},{"type":"codeVoice","code":"List"},{"type":"text","text":"s to iterate over an array of "},{"type":"codeVoice","code":"todos"},{"type":"text","text":" and embedding it in a "},{"type":"codeVoice","code":"NavigationView"},{"type":"text","text":" with a "},{"type":"codeVoice","code":".navigationTitle"},{"type":"text","text":"."}],"identifier":"doc:\/\/swiftinsg\/tutorials\/swiftinsg\/0-TodoLists#Creating-a-Project","kind":"section","type":"section","url":"\/tutorials\/swiftinsg\/0-todolists#Creating-a-Project"},"../friends":{"title":"Friends App","titleInlineContent":[{"type":"text","text":"Friends App"}],"type":"link","identifier":"..\/friends","url":"..\/friends"},"../quiz-app":{"title":"Quiz App","titleInlineContent":[{"type":"text","text":"Quiz App"}],"type":"link","identifier":"..\/quiz-app","url":"..\/quiz-app"},"todo-ch1-lists-s4-0-Preview.png":{"alt":"","type":"image","identifier":"todo-ch1-lists-s4-0-Preview.png","variants":[{"url":"\/images\/todo-ch1-lists-s4-0-Preview.png","traits":["1x","light"]}]},"todo-ch1-lists-s2-2-save.png":{"alt":"","type":"image","identifier":"todo-ch1-lists-s2-2-save.png","variants":[{"url":"\/images\/todo-ch1-lists-s2-2-save.png","traits":["1x","light"]},{"url":"\/images\/todo-ch1-lists-s2-2-save~dark.png","traits":["1x","dark"]}]},"doc://swiftinsg/tutorials/swiftinsg/3-TodoNew#Dismissing-the-Modal":{"role":"pseudoSymbol","title":"Dismissing the Modal","abstract":[{"type":"text","text":"This tutorial covers how to use "},{"type":"codeVoice","code":"Form"},{"type":"text","text":"s, modals and "},{"type":"codeVoice","code":"@Binding"},{"type":"text","text":" variables to create a new "},{"type":"codeVoice","code":"Todo"},{"type":"text","text":"."}],"identifier":"doc:\/\/swiftinsg\/tutorials\/swiftinsg\/3-TodoNew#Dismissing-the-Modal","kind":"section","type":"section","url":"\/tutorials\/swiftinsg\/3-todonew#Dismissing-the-Modal"},"shared-select app.png":{"alt":"Select App","type":"image","identifier":"shared-select app.png","variants":[{"url":"\/images\/shared-select%20app.png","traits":["1x","light"]},{"url":"\/images\/shared-select%20app~dark.png","traits":["1x","dark"]}]},"todo-ch1-lists-s4-2-ContentView.swift":{"syntax":"swift","content":["import SwiftUI","","struct ContentView: View {","    ","    @State var todos = [Todo(title: \"Feed the cat\"),","                        Todo(title: \"Play with cat\"),","                        Todo(title: \"Get allergies\"),","                        Todo(title: \"Run away from cat\"),","                        Todo(title: \"Get a new cat\")]","    ","    var body: some View {","        NavigationView {","            List(todos) { todo in","                Text(todo.title)","            }","            .navigationTitle(\"Todos\")","        }","    }","}","","struct ContentView_Previews: PreviewProvider {","    static var previews: some View {","        ContentView()","    }","}"],"fileName":"ContentView.swift","identifier":"todo-ch1-lists-s4-2-ContentView.swift","type":"file","fileType":"swift","highlights":[{"line":16}]},"todo-ch1-lists-s2-6-Todo.swift":{"syntax":"swift","content":["import Foundation","","struct Todo: Identifiable {","    var id = UUID()","    ","    var title: String","    var isCompleted = false","}"],"fileName":"Todo.swift","identifier":"todo-ch1-lists-s2-6-Todo.swift","type":"file","fileType":"swift","highlights":[{"line":3},{"line":4},{"line":5}]},"doc://swiftinsg/tutorials/swiftinsg/4-TodoPersistence#Conforming-to-Codable":{"role":"pseudoSymbol","title":"Conforming to Codable","abstract":[{"type":"text","text":"Persistence is not that hard, all you need is some… persistence. HAHHAHAHHAHHHAHAHAH. Persistence refers to the concept of storing data in a way that they will remain there even if you close the app. Currently, when you close the app, any data is thrown away. If you create a new todo, it gets thrown away when you close the app. We want data to persist when the app is closed otherwise the todo list app will be as forgetful as you."}],"identifier":"doc:\/\/swiftinsg\/tutorials\/swiftinsg\/4-TodoPersistence#Conforming-to-Codable","kind":"section","type":"section","url":"\/tutorials\/swiftinsg\/4-todopersistence#Conforming-to-Codable"},"todo-ch1-lists-s1-3-create project.png":{"alt":"Project Created","type":"image","identifier":"todo-ch1-lists-s1-3-create project.png","variants":[{"url":"\/images\/todo-ch1-lists-s1-3-create%20project.png","traits":["1x","light"]},{"url":"\/images\/todo-ch1-lists-s1-3-create%20project~dark.png","traits":["1x","dark"]}]},"todo-ch1-lists-s4-1-ContentView.swift":{"syntax":"swift","content":["import SwiftUI","","struct ContentView: View {","    ","    @State var todos = [Todo(title: \"Feed the cat\"),","                        Todo(title: \"Play with cat\"),","                        Todo(title: \"Get allergies\"),","                        Todo(title: \"Run away from cat\"),","                        Todo(title: \"Get a new cat\")]","    ","    var body: some View {","        NavigationView {","            List(todos) { todo in","                Text(todo.title)","            }","        }","    }","}","","struct ContentView_Previews: PreviewProvider {","    static var previews: some View {","        ContentView()","    }","}"],"fileName":"ContentView.swift","identifier":"todo-ch1-lists-s4-1-ContentView.swift","type":"file","fileType":"swift","highlights":[{"line":12},{"line":13},{"line":14},{"line":15}]},"shared-new project.png":{"alt":"Create new project","type":"image","identifier":"shared-new project.png","variants":[{"url":"\/images\/shared-new%20project.png","traits":["1x","light"]},{"url":"\/images\/shared-new%20project~dark.png","traits":["1x","dark"]}]},"doc://swiftinsg/tutorials/swiftinsg/3-TodoNew#Saving-a-Todo":{"role":"pseudoSymbol","title":"Saving a Todo","abstract":[{"type":"text","text":"This tutorial covers how to use "},{"type":"codeVoice","code":"Form"},{"type":"text","text":"s, modals and "},{"type":"codeVoice","code":"@Binding"},{"type":"text","text":" variables to create a new "},{"type":"codeVoice","code":"Todo"},{"type":"text","text":"."}],"identifier":"doc:\/\/swiftinsg\/tutorials\/swiftinsg\/3-TodoNew#Saving-a-Todo","kind":"section","type":"section","url":"\/tutorials\/swiftinsg\/3-todonew#Saving-a-Todo"},"doc://swiftinsg/tutorials/swiftinsg/0-TodoLists#Embedding-in-a-NavigationView":{"role":"pseudoSymbol","title":"Embedding in a NavigationView","abstract":[{"type":"text","text":"This tutorial covers how to use create a "},{"type":"codeVoice","code":"Todo"},{"type":"text","text":" struct, using "},{"type":"codeVoice","code":"List"},{"type":"text","text":"s to iterate over an array of "},{"type":"codeVoice","code":"todos"},{"type":"text","text":" and embedding it in a "},{"type":"codeVoice","code":"NavigationView"},{"type":"text","text":" with a "},{"type":"codeVoice","code":".navigationTitle"},{"type":"text","text":"."}],"identifier":"doc:\/\/swiftinsg\/tutorials\/swiftinsg\/0-TodoLists#Embedding-in-a-NavigationView","kind":"section","type":"section","url":"\/tutorials\/swiftinsg\/0-todolists#Embedding-in-a-NavigationView"},"doc://swiftinsg/tutorials/swiftinsg/0-TodoLists#Creating-a-List":{"role":"pseudoSymbol","title":"Creating a List","abstract":[{"type":"text","text":"This tutorial covers how to use create a "},{"type":"codeVoice","code":"Todo"},{"type":"text","text":" struct, using "},{"type":"codeVoice","code":"List"},{"type":"text","text":"s to iterate over an array of "},{"type":"codeVoice","code":"todos"},{"type":"text","text":" and embedding it in a "},{"type":"codeVoice","code":"NavigationView"},{"type":"text","text":" with a "},{"type":"codeVoice","code":".navigationTitle"},{"type":"text","text":"."}],"identifier":"doc:\/\/swiftinsg\/tutorials\/swiftinsg\/0-TodoLists#Creating-a-List","kind":"section","type":"section","url":"\/tutorials\/swiftinsg\/0-todolists#Creating-a-List"},"todo-ch1-lists-s4-0-ContentView.swift":{"syntax":"swift","content":["import SwiftUI","","struct ContentView: View {","    ","    @State var todos = [Todo(title: \"Feed the cat\"),","                        Todo(title: \"Play with cat\"),","                        Todo(title: \"Get allergies\"),","                        Todo(title: \"Run away from cat\"),","                        Todo(title: \"Get a new cat\")]","    ","    var body: some View {","        List(todos) { todo in","            Text(todo.title)","        }","    }","}","","struct ContentView_Previews: PreviewProvider {","    static var previews: some View {","        ContentView()","    }","}"],"fileName":"ContentView.swift","identifier":"todo-ch1-lists-s4-0-ContentView.swift","type":"file","fileType":"swift","highlights":[]},"todo-ch1-lists-s3-1-ContentView.swift":{"syntax":"swift","content":["import SwiftUI","","struct ContentView: View {","    ","    @State var todos = [Todo(title: \"Feed the cat\"),","                        Todo(title: \"Play with cat\"),","                        Todo(title: \"Get allergies\"),","                        Todo(title: \"Run away from cat\"),","                        Todo(title: \"Get a new cat\")]","    ","    var body: some View {","        List(todos) { todo in","            Text(todo.title)","        }","    }","}","","struct ContentView_Previews: PreviewProvider {","    static var previews: some View {","        ContentView()","    }","}"],"fileName":"ContentView.swift","identifier":"todo-ch1-lists-s3-1-ContentView.swift","type":"file","fileType":"swift","highlights":[{"line":12},{"line":13},{"line":14}]},"todo-ch1-lists-s1-2-configuring project.png":{"alt":"Configure App","type":"image","identifier":"todo-ch1-lists-s1-2-configuring project.png","variants":[{"url":"\/images\/todo-ch1-lists-s1-2-configuring%20project.png","traits":["1x","light"]},{"url":"\/images\/todo-ch1-lists-s1-2-configuring%20project~dark.png","traits":["1x","dark"]}]},"todo-ch1-lists-s4-1-Preview.png":{"alt":"","type":"image","identifier":"todo-ch1-lists-s4-1-Preview.png","variants":[{"url":"\/images\/todo-ch1-lists-s4-1-Preview.png","traits":["1x","light"]}]},"../tutorials/friends":{"title":"Friends tutorial","titleInlineContent":[{"type":"text","text":"Friends tutorial"}],"type":"link","identifier":"..\/tutorials\/friends","url":"..\/tutorials\/friends"},"doc://swiftinsg/tutorials/swiftinsg/1-TodoStrikethrough":{"role":"project","title":"Striking Off Todos","estimatedTime":"20min","abstract":[{"type":"text","text":"Add a checkmark using SF Symbols and use the "},{"type":"codeVoice","code":".strikethrough"},{"type":"text","text":" modifier to add a strikethrough when the todo "},{"type":"codeVoice","code":"isCompleted"},{"type":"text","text":"."}],"identifier":"doc:\/\/swiftinsg\/tutorials\/swiftinsg\/1-TodoStrikethrough","kind":"project","type":"topic","url":"\/tutorials\/swiftinsg\/1-todostrikethrough"},"todo-ch1-lists-s2-7-Preview.png":{"alt":"","type":"image","identifier":"todo-ch1-lists-s2-7-Preview.png","variants":[{"url":"\/images\/todo-ch1-lists-s2-7-Preview.png","traits":["1x","light"]}]},"doc://swiftinsg/tutorials/swiftinsg/3-TodoNew#Creating-a-new-SwiftUI-View":{"role":"pseudoSymbol","title":"Creating a new SwiftUI View","abstract":[{"type":"text","text":"This tutorial covers how to use "},{"type":"codeVoice","code":"Form"},{"type":"text","text":"s, modals and "},{"type":"codeVoice","code":"@Binding"},{"type":"text","text":" variables to create a new "},{"type":"codeVoice","code":"Todo"},{"type":"text","text":"."}],"identifier":"doc:\/\/swiftinsg\/tutorials\/swiftinsg\/3-TodoNew#Creating-a-new-SwiftUI-View","kind":"section","type":"section","url":"\/tutorials\/swiftinsg\/3-todonew#Creating-a-new-SwiftUI-View"},"doc://swiftinsg/tutorials/swiftinsg/4-TodoPersistence#Save-and-Load-Data":{"role":"pseudoSymbol","title":"Save and Load Data","abstract":[{"type":"text","text":"Persistence is not that hard, all you need is some… persistence. HAHHAHAHHAHHHAHAHAH. Persistence refers to the concept of storing data in a way that they will remain there even if you close the app. Currently, when you close the app, any data is thrown away. If you create a new todo, it gets thrown away when you close the app. We want data to persist when the app is closed otherwise the todo list app will be as forgetful as you."}],"identifier":"doc:\/\/swiftinsg\/tutorials\/swiftinsg\/4-TodoPersistence#Save-and-Load-Data","kind":"section","type":"section","url":"\/tutorials\/swiftinsg\/4-todopersistence#Save-and-Load-Data"},"doc://swiftinsg/tutorials/swiftinsg/1-TodoStrikethrough#Adding-a-Strikethrough":{"role":"pseudoSymbol","title":"Adding a Strikethrough","abstract":[{"type":"text","text":"Add a checkmark using SF Symbols and use the "},{"type":"codeVoice","code":".strikethrough"},{"type":"text","text":" modifier to add a strikethrough when the todo "},{"type":"codeVoice","code":"isCompleted"},{"type":"text","text":"."}],"identifier":"doc:\/\/swiftinsg\/tutorials\/swiftinsg\/1-TodoStrikethrough#Adding-a-Strikethrough","kind":"section","type":"section","url":"\/tutorials\/swiftinsg\/1-todostrikethrough#Adding-a-Strikethrough"},"todo-ch1-lists-s2-7-ContentView.swift":{"syntax":"swift","content":["import SwiftUI","","struct ContentView: View {","    var body: some View {","        Text(\"Hello, world!\")","            .padding()","    }","}","","struct ContentView_Previews: PreviewProvider {","    static var previews: some View {","        ContentView()","    }","}"],"fileName":"ContentView.swift","identifier":"todo-ch1-lists-s2-7-ContentView.swift","type":"file","fileType":"swift","highlights":[]},"doc://swiftinsg/tutorials/Todo/Creating-a-Todo-List-app":{"role":"article","title":"Creating a Todo List app","abstract":[],"identifier":"doc:\/\/swiftinsg\/tutorials\/Todo\/Creating-a-Todo-List-app","kind":"article","type":"topic","url":"\/tutorials\/todo\/creating-a-todo-list-app"},"doc://swiftinsg/tutorials/swiftinsg/2-TodoManipulation#Moving-Todos":{"role":"pseudoSymbol","title":"Moving Todos","abstract":[{"type":"text","text":"Use an "},{"type":"codeVoice","code":"ForEach"},{"type":"text","text":" and "},{"type":"codeVoice","code":"EditButton()"},{"type":"text","text":" to allow users to move and delete todos."}],"identifier":"doc:\/\/swiftinsg\/tutorials\/swiftinsg\/2-TodoManipulation#Moving-Todos","kind":"section","type":"section","url":"\/tutorials\/swiftinsg\/2-todomanipulation#Moving-Todos"},"todo-ch1-lists-s2-5-Todo.swift":{"syntax":"swift","content":["import Foundation","","struct Todo {","    var title: String","    var isCompleted = false","}"],"fileName":"Todo.swift","identifier":"todo-ch1-lists-s2-5-Todo.swift","type":"file","fileType":"swift","highlights":[{"line":4},{"line":5}]},"doc://swiftinsg/tutorials/swiftinsg/3-TodoNew#Presenting-the-Modal":{"role":"pseudoSymbol","title":"Presenting the Modal","abstract":[{"type":"text","text":"This tutorial covers how to use "},{"type":"codeVoice","code":"Form"},{"type":"text","text":"s, modals and "},{"type":"codeVoice","code":"@Binding"},{"type":"text","text":" variables to create a new "},{"type":"codeVoice","code":"Todo"},{"type":"text","text":"."}],"identifier":"doc:\/\/swiftinsg\/tutorials\/swiftinsg\/3-TodoNew#Presenting-the-Modal","kind":"section","type":"section","url":"\/tutorials\/swiftinsg\/3-todonew#Presenting-the-Modal"},"doc://swiftinsg/tutorials/swiftinsg/3-TodoNew":{"role":"project","title":"Creating New Todos","estimatedTime":"25min","abstract":[{"type":"text","text":"This tutorial covers how to use "},{"type":"codeVoice","code":"Form"},{"type":"text","text":"s, modals and "},{"type":"codeVoice","code":"@Binding"},{"type":"text","text":" variables to create a new "},{"type":"codeVoice","code":"Todo"},{"type":"text","text":"."}],"identifier":"doc:\/\/swiftinsg\/tutorials\/swiftinsg\/3-TodoNew","kind":"project","type":"topic","url":"\/tutorials\/swiftinsg\/3-todonew"},"doc://swiftinsg/tutorials/swiftinsg/0-TodoLists":{"role":"project","title":"Listing Todos","estimatedTime":"20min","abstract":[{"type":"text","text":"This tutorial covers how to use create a "},{"type":"codeVoice","code":"Todo"},{"type":"text","text":" struct, using "},{"type":"codeVoice","code":"List"},{"type":"text","text":"s to iterate over an array of "},{"type":"codeVoice","code":"todos"},{"type":"text","text":" and embedding it in a "},{"type":"codeVoice","code":"NavigationView"},{"type":"text","text":" with a "},{"type":"codeVoice","code":".navigationTitle"},{"type":"text","text":"."}],"identifier":"doc:\/\/swiftinsg\/tutorials\/swiftinsg\/0-TodoLists","kind":"project","type":"topic","url":"\/tutorials\/swiftinsg\/0-todolists"},"todo-ch1-lists-s4-2-Preview.png":{"alt":"","type":"image","identifier":"todo-ch1-lists-s4-2-Preview.png","variants":[{"url":"\/images\/todo-ch1-lists-s4-2-Preview.png","traits":["1x","light"]}]},"doc://swiftinsg/tutorials/swiftinsg/1-TodoStrikethrough#Adding-a-Checkmark":{"role":"pseudoSymbol","title":"Adding a Checkmark","abstract":[{"type":"text","text":"Add a checkmark using SF Symbols and use the "},{"type":"codeVoice","code":".strikethrough"},{"type":"text","text":" modifier to add a strikethrough when the todo "},{"type":"codeVoice","code":"isCompleted"},{"type":"text","text":"."}],"identifier":"doc:\/\/swiftinsg\/tutorials\/swiftinsg\/1-TodoStrikethrough#Adding-a-Checkmark","kind":"section","type":"section","url":"\/tutorials\/swiftinsg\/1-todostrikethrough#Adding-a-Checkmark"},"todo-ch1-lists-s3-0-Preview.png":{"alt":"","type":"image","identifier":"todo-ch1-lists-s3-0-Preview.png","variants":[{"url":"\/images\/todo-ch1-lists-s3-0-Preview.png","traits":["1x","light"]}]},"doc://swiftinsg/tutorials/swiftinsg/4-TodoPersistence#Creating-a-Task-Model":{"role":"pseudoSymbol","title":"Creating a Task Model","abstract":[{"type":"text","text":"Persistence is not that hard, all you need is some… persistence. HAHHAHAHHAHHHAHAHAH. Persistence refers to the concept of storing data in a way that they will remain there even if you close the app. Currently, when you close the app, any data is thrown away. If you create a new todo, it gets thrown away when you close the app. We want data to persist when the app is closed otherwise the todo list app will be as forgetful as you."}],"identifier":"doc:\/\/swiftinsg\/tutorials\/swiftinsg\/4-TodoPersistence#Creating-a-Task-Model","kind":"section","type":"section","url":"\/tutorials\/swiftinsg\/4-todopersistence#Creating-a-Task-Model"},"todo-ch1-lists-s2-4-Todo.swift":{"syntax":"swift","content":["import Foundation","","struct Todo {","    ","}"],"fileName":"Todo.swift","identifier":"todo-ch1-lists-s2-4-Todo.swift","type":"file","fileType":"swift","highlights":[{"line":2},{"line":3},{"line":4},{"line":5}]},"doc://swiftinsg/tutorials/swiftinsg/2-TodoManipulation":{"role":"project","title":"Moving & Deleting Todos","estimatedTime":"25min","abstract":[{"type":"text","text":"Use an "},{"type":"codeVoice","code":"ForEach"},{"type":"text","text":" and "},{"type":"codeVoice","code":"EditButton()"},{"type":"text","text":" to allow users to move and delete todos."}],"identifier":"doc:\/\/swiftinsg\/tutorials\/swiftinsg\/2-TodoManipulation","kind":"project","type":"topic","url":"\/tutorials\/swiftinsg\/2-todomanipulation"},"todo-ch1-lists-s3-1-Preview.png":{"alt":"","type":"image","identifier":"todo-ch1-lists-s3-1-Preview.png","variants":[{"url":"\/images\/todo-ch1-lists-s3-1-Preview.png","traits":["1x","light"]}]},"doc://swiftinsg/tutorials/swiftinsg/2-TodoManipulation#Deleting-a-Todo":{"role":"pseudoSymbol","title":"Deleting a Todo","abstract":[{"type":"text","text":"Use an "},{"type":"codeVoice","code":"ForEach"},{"type":"text","text":" and "},{"type":"codeVoice","code":"EditButton()"},{"type":"text","text":" to allow users to move and delete todos."}],"identifier":"doc:\/\/swiftinsg\/tutorials\/swiftinsg\/2-TodoManipulation#Deleting-a-Todo","kind":"section","type":"section","url":"\/tutorials\/swiftinsg\/2-todomanipulation#Deleting-a-Todo"},"doc://swiftinsg/tutorials/swiftinsg/0-TodoLists#Create-a-Todo":{"role":"pseudoSymbol","title":"Create a Todo","abstract":[{"type":"text","text":"This tutorial covers how to use create a "},{"type":"codeVoice","code":"Todo"},{"type":"text","text":" struct, using "},{"type":"codeVoice","code":"List"},{"type":"text","text":"s to iterate over an array of "},{"type":"codeVoice","code":"todos"},{"type":"text","text":" and embedding it in a "},{"type":"codeVoice","code":"NavigationView"},{"type":"text","text":" with a "},{"type":"codeVoice","code":".navigationTitle"},{"type":"text","text":"."}],"identifier":"doc:\/\/swiftinsg\/tutorials\/swiftinsg\/0-TodoLists#Create-a-Todo","kind":"section","type":"section","url":"\/tutorials\/swiftinsg\/0-todolists#Create-a-Todo"},"https://developer.apple.com/documentation/swift/identifiable/":{"title":"Identifiable","titleInlineContent":[{"type":"codeVoice","code":"Identifiable"}],"type":"link","identifier":"https:\/\/developer.apple.com\/documentation\/swift\/identifiable\/","url":"https:\/\/developer.apple.com\/documentation\/swift\/identifiable\/"},"shared-new swift file.png":{"alt":"","type":"image","identifier":"shared-new swift file.png","variants":[{"url":"\/images\/shared-new%20swift%20file.png","traits":["1x","light"]},{"url":"\/images\/shared-new%20swift%20file~dark.png","traits":["1x","dark"]}]},"todo-ch1-lists-s2-3-Todo.swift":{"syntax":"swift","content":["import Foundation"],"fileName":"Todo.swift","identifier":"todo-ch1-lists-s2-3-Todo.swift","type":"file","fileType":"swift","highlights":[]},"todo-ch1-lists-s2-0-new file.png":{"alt":"","type":"image","identifier":"todo-ch1-lists-s2-0-new file.png","variants":[{"url":"\/images\/todo-ch1-lists-s2-0-new%20file.png","traits":["1x","light"]},{"url":"\/images\/todo-ch1-lists-s2-0-new%20file~dark.png","traits":["1x","dark"]}]},"doc://swiftinsg/tutorials/swiftinsg/1-TodoStrikethrough#Toggling-a-Todo":{"role":"pseudoSymbol","title":"Toggling a Todo","abstract":[{"type":"text","text":"Add a checkmark using SF Symbols and use the "},{"type":"codeVoice","code":".strikethrough"},{"type":"text","text":" modifier to add a strikethrough when the todo "},{"type":"codeVoice","code":"isCompleted"},{"type":"text","text":"."}],"identifier":"doc:\/\/swiftinsg\/tutorials\/swiftinsg\/1-TodoStrikethrough#Toggling-a-Todo","kind":"section","type":"section","url":"\/tutorials\/swiftinsg\/1-todostrikethrough#Toggling-a-Todo"},"doc://swiftinsg/tutorials/swiftinsg/3-TodoNew#Embedding-in-NavigationView":{"role":"pseudoSymbol","title":"Embedding in NavigationView","abstract":[{"type":"text","text":"This tutorial covers how to use "},{"type":"codeVoice","code":"Form"},{"type":"text","text":"s, modals and "},{"type":"codeVoice","code":"@Binding"},{"type":"text","text":" variables to create a new "},{"type":"codeVoice","code":"Todo"},{"type":"text","text":"."}],"identifier":"doc:\/\/swiftinsg\/tutorials\/swiftinsg\/3-TodoNew#Embedding-in-NavigationView","kind":"section","type":"section","url":"\/tutorials\/swiftinsg\/3-todonew#Embedding-in-NavigationView"},"todo-ch1-lists-s2-8-Preview.png":{"alt":"","type":"image","identifier":"todo-ch1-lists-s2-8-Preview.png","variants":[{"url":"\/images\/todo-ch1-lists-s2-8-Preview.png","traits":["1x","light"]}]},"doc://swiftinsg/tutorials/Todo":{"role":"overview","title":"Building a Todo List App","abstract":[{"type":"text","text":"This tutorial recaps on the concepts taught in the "},{"type":"reference","isActive":true,"identifier":"..\/tutorials\/friends"},{"type":"text","text":" such as "},{"type":"codeVoice","code":"@Binding"},{"type":"text","text":" variables, "},{"type":"codeVoice","code":"List"},{"type":"text","text":"s, "},{"type":"codeVoice","code":"Form"},{"type":"text","text":"s, and persistence."}],"identifier":"doc:\/\/swiftinsg\/tutorials\/Todo","kind":"overview","type":"topic","url":"\/tutorials\/todo"},"todo-ch1-lists-s2-8-ContentView.swift":{"syntax":"swift","content":["import SwiftUI","","struct ContentView: View {","    ","    @State var todos = [Todo(title: \"Feed the cat\"),","                        Todo(title: \"Play with cat\"),","                        Todo(title: \"Get allergies\"),","                        Todo(title: \"Run away from cat\"),","                        Todo(title: \"Get a new cat\")]","    ","    var body: some View {","        Text(\"Hello, world!\")","            .padding()","    }","}","","struct ContentView_Previews: PreviewProvider {","    static var previews: some View {","        ContentView()","    }","}"],"fileName":"ContentView.swift","identifier":"todo-ch1-lists-s2-8-ContentView.swift","type":"file","fileType":"swift","highlights":[{"line":4},{"line":5},{"line":6},{"line":7},{"line":8},{"line":9},{"line":10}]}}}